{
    "title": "儒勒·凡尔纳科幻绘本系列(全套5册)",
    "bookInfo": {
        "作者": "改编：安东尼斯·帕帕塞奥多罗 / 插图：艾丽斯·萨玛尔茨 / 原作者：儒勒·凡尔纳",
        "出版社": "中信出版社",
        "译者": "吴华",
        "出版年": "2018-2-1",
        "页数": "170",
        "定价": "175元",
        "装帧": "精装",
        "丛书": "儒勒·凡尔纳科幻绘本系列",
        "ISBN": "9787508686561"
    },
    "related_intro": "\n        \n          \n.intro p{text-indent:2em;word-break:normal;}\n\n\n    《儒勒·凡尔纳科幻绘本系列》是一套科学启蒙、激发想象的故事绘本，适合3—8岁孩子阅读。该系列包含《海底两万里》《八十天环游地球》《地心游记》《从地球到月球》《征服者罗比尔》5个传奇色彩与科学精神的冒险故事。    原著故事由“现代科学幻想小说之父”儒勒·凡尔纳创作，这套绘本版则由两位国际大奖得主改编、绘图，他们将原著小说以绘本的形式再现，保留核心思想、降低阅读难度、突出儿童兴趣、绘制精美插画，使其符合3—8岁孩子阅读需求。    该系列通过充满想象的故事，激发阅读兴趣、提高阅读能力、培养阅读习惯，帮助孩子逐步走向独立阅读。同时，在孩子还保留着与生俱来的好奇心时，提前为科学素质教育打下基础：在知识层面，增加孩子对世界的认知和好奇；在情感层面，引发孩子对科学的喜爱和热情；在方法层面，培养科学素养，训练思式。    《海底两万里》    各地海洋惊现奇异物体！忽而现身大西洋，忽而又到太平洋。这海怪渐渐成了海上贸易和交通的威胁，渔民海员人心惶惶……它究竟是什么？    《八十天环游地球》    “环游地球一周只要八十天就够了。”英国大富翁斐利亚·福格和朋友打赌，并押上了自己全部的财产。福格先生事事计划周密，他能够按时完成旅行吗？    《地心游记》    “穿过它向下，便可抵达地心……”林登布罗克从前人留下的神秘文字中启示，决定带领侄子阿克塞尔和向导汉斯，进行一次深入地心的科学探险之旅……    《从地球到月球》    战争结束了，人们重获和平！武器发明家因比·巴比凯恩却没了用武之地。他整日无所事事，于是突发奇想：建造一门大炮，将炮弹发射到月亮上去……    《征服者罗比尔》    全世界上空怪事连连！号角乐声缥缈而来，不明物体时隐时现。各地高建筑物顶端都相继飘起了同样的旗帜。而那时，飞行器尚未发明……        .......\n\n        \n      ",
    "star_rate": {
        "five_star_rate": "74.5%",
        "four_star_rate": "21.6%",
        "three_star_rate": "2.0%",
        "two_star_rate": "0.0%",
        "one_star_rate": "2.0%"
    },
    "authors": [],
    "shops": [],
    "url": "https://book.douban.com/subject/30184485/",
    "douban_id": "30184485",
    "menu": [
        "",
        "        《海底两万里》",
        "        《八十天环游地球》",
        "        《地心游记》",
        "        《从地球到月球》",
        "        《征服者罗比尔》",
        "     · · · · · ·     (收起)",
        ""
    ],
    "img_link": "https://img2.doubanio.com/view/subject/s/public/s29729461.jpg",
    "info_a_labels_data": [
        {
            "text": "改编：安东尼斯·帕帕塞奥多罗",
            "link": "https://book.douban.com/search/%E6%94%B9%E7%BC%96%EF%BC%9A%E5%AE%89%E4%B8%9C%E5%B0%BC%E6%96%AF%C2%B7%E5%B8%95%E5%B8%95%E5%A1%9E%E5%A5%A5%E5%A4%9A%E7%BD%97"
        },
        {
            "text": "插图：艾丽斯·萨玛尔茨",
            "link": "https://book.douban.com/search/%E6%8F%92%E5%9B%BE%EF%BC%9A%E8%89%BE%E4%B8%BD%E6%96%AF%C2%B7%E8%90%A8%E7%8E%9B%E5%B0%94%E8%8C%A8"
        },
        {
            "text": "原作者：儒勒·凡尔纳",
            "link": "https://book.douban.com/search/%E5%8E%9F%E4%BD%9C%E8%80%85%EF%BC%9A%E5%84%92%E5%8B%92%C2%B7%E5%87%A1%E5%B0%94%E7%BA%B3"
        },
        {
            "text": "中信出版社",
            "link": "https://book.douban.com/press/2400"
        },
        {
            "text": "吴华",
            "link": "https://book.douban.com/search/%E5%90%B4%E5%8D%8E"
        },
        {
            "text": "儒勒·凡尔纳科幻绘本系列",
            "link": "https://book.douban.com/series/46534"
        }
    ],
    "tag": "科幻"
}