{
    "title": "我的家在蜜糖湾",
    "bookInfo": {
        "作者": "[美] 海伦·库伯",
        "出版社": "江苏文艺出版社",
        "译者": "余佑兰",
        "出版年": "2011-1",
        "页数": "344",
        "定价": "29.80元",
        "装帧": "Paperback",
        "丛书": "博集天卷·外国文学馆",
        "ISBN": "9787539939902"
    },
    "related_intro": null,
    "star_rate": {
        "five_star_rate": "25.9%",
        "four_star_rate": "41.6%",
        "three_star_rate": "29.4%",
        "two_star_rate": "2.0%",
        "one_star_rate": "1.0%"
    },
    "authors": [],
    "shops": [],
    "url": "https://book.douban.com/subject/5402675/",
    "douban_id": "5402675",
    "menu": [
        "",
        "        蜜糖湾，利比里亚，一九七三 / 001",
        "        横越大西洋，纽约，一八二〇 / 027",
        "        尤尼丝，蜜糖湾，一九七四 / 034",
        "        蜜糖湾，利比里亚，一九七四 / 044",
        "        蜜糖湾，利比里亚，一九七五 / 062",
        "        蜜糖湾，利比里亚，一九七五/ 071",
        "        蒙罗维亚，利比里亚，一九七七 / 092",
        "        蜜糖湾，利比里亚，一九七七 / 105",
        "        蒙罗维亚，利比里亚，一九七八 / 118",
        "        蜜糖湾，利比里亚，一九七九 / 130",
        "        蜜糖湾，利比里亚，一九七九/ 146",
        "        蜜糖湾，利比里亚，一九八〇年四月十二日 / 160",
        "        蒙罗维亚，利比里亚，一九八〇年四月二十二日 / 175",
        "        诺克斯维尔，田纳西州，一九八〇 / 190",
        "        格林斯堡，北卡罗来纳，一九八一 / 209",
        "        格林斯堡，北卡罗来纳，一九八二 / 218",
        "        蒙罗维亚，利比里亚，一九八二～一九八三 / 230",
        "        教堂山，北卡罗来纳，一九八三～一九八七 / 235",
        "        一九八五 / 245",
        "        普洛维登斯市，罗德岛，一九八七～一九九二 / 256",
        "        蒙罗维亚，利比里亚，一九八八～一九九四 / 275",
        "        世界，一九九四～二〇〇三 / 280",
        "        伊拉克，二〇〇三年二～四月 / 295",
        "        蒙罗维亚，二〇〇三年九月 / 309",
        "        蒙罗维亚，二〇〇三年九月 / 329",
        "     · · · · · ·     (收起)",
        ""
    ],
    "img_link": "https://img2.doubanio.com/view/subject/s/public/s6261581.jpg",
    "info_a_labels_data": [
        {
            "text": "[美] 海伦·库伯",
            "link": "https://book.douban.com/search/%E6%B5%B7%E4%BC%A6%C2%B7%E5%BA%93%E4%BC%AF"
        },
        {
            "text": "江苏文艺出版社",
            "link": "https://book.douban.com/press/2720"
        },
        {
            "text": "余佑兰",
            "link": "https://book.douban.com/search/%E4%BD%99%E4%BD%91%E5%85%B0"
        },
        {
            "text": "博集天卷·外国文学馆",
            "link": "https://book.douban.com/series/4846"
        }
    ],
    "tag": "回忆录"
}