{
    "title": "那些年，我们在一起",
    "bookInfo": {
        "作者": "魏雪明",
        "出版社": "现代出版社",
        "出版年": "2014-2-1",
        "页数": "224",
        "定价": "32.80元",
        "装帧": "平装",
        "ISBN": "9787514322156"
    },
    "related_intro": null,
    "star_rate": {
        "five_star_rate": "16.7%",
        "four_star_rate": "41.7%",
        "three_star_rate": "37.5%",
        "two_star_rate": "0.0%",
        "one_star_rate": "4.2%"
    },
    "authors": [],
    "shops": [
        {
            "name": "京东商城",
            "price": "28.18元",
            "link": "https://book.douban.com/link2/?lowest=1800&pre=0&vendor=jingdong&srcpage=subject&price=2818&pos=1&url=https%3A%2F%2Fitem.jd.com%2F10066175128300.html&cntvendor=2&srcsubj=25808877&type=bkbuy&subject=25808877"
        },
        {
            "name": "中图网",
            "price": "18.00元",
            "link": "https://book.douban.com/link2/?lowest=1800&pre=0&vendor=bookschina&srcpage=subject&price=1800&pos=2&url=http%3A%2F%2Fwww.bookschina.com%2Funion%2Fubook.asp%3Fadservice%3D354872%26tourl%3Dhttp%3A%2F%2Fwww.bookschina.com%2F6470119.htm&cntvendor=2&srcsubj=25808877&type=bkbuy&subject=25808877"
        }
    ],
    "url": "https://book.douban.com/subject/25808877/",
    "douban_id": "25808877",
    "menu": [
        "",
        "        引子：上大学前",
        "        滚蛋吧，高考！",
        "        去死吧，初恋！",
        "        第一章\t哇噻！大学！",
        "        学长的接待",
        "        大学我来啦",
        "        飞机和TOM",
        "        北京来的新同学",
        "        同学阿雷",
        "        同学大头",
        "        大学老师",
        "        大学社团",
        "        我的PAPA",
        "        班干部选举",
        "        哪哪都是长龙",
        "        第二章　军训神马的最要命",
        "        站军姿",
        "        紧急集合",
        "        向左转",
        "        拉歌",
        "        小屎的病假条",
        "        走正步",
        "        战友之战",
        "        第三章　不想在大学里变态，就乖乖谈恋爱……",
        "        学妹争夺战",
        "        为什么我追不到学妹",
        "        谢谢你的表白",
        "        我的女朋友",
        "        优质男友",
        "        作家是怎么炼成的",
        "        小屎的女朋友",
        "        失恋",
        "        亲爱的,帮我带一包卫生巾",
        "        视频",
        "        卧谈会",
        "        第四章\t敢不敢再懒一点？",
        "        爱的理由",
        "        饥饿战争",
        "        下午有课吗?",
        "        显摆的后果",
        "        公共财产",
        "        咱能靠谱点吗?",
        "        寝室长",
        "        洗衣服引发的血案",
        "        真爷们",
        "        火车票",
        "        第五章　那些年我们在一起",
        "        超女后援团",
        "        篮球赛",
        "        没人在乎我",
        "        史上最恐怖的恐怖片",
        "        什么情况？",
        "        “不看球会死”协会",
        "        最郁闷的事",
        "        我为什么不能好好学习？",
        "        我感冒了",
        "        外教",
        "        ",
        "        第六章　不挂科的战斗",
        "        高数考试",
        "        防挂宝典",
        "        1马哲考试",
        "        查分",
        "        医院的特殊期",
        "        小屎的四级",
        "        四级荣耀",
        "        持续牛逼得办法",
        "        挂科的福利",
        "        考研剩斗士",
        "        第七章　时候该滚蛋了！",
        "        毕业论文",
        "        告别帖",
        "        跳蚤市场",
        "        毕业分手季",
        "        求抱抱",
        "        考研面试",
        "        应聘",
        "        毕业合照",
        "        散伙饭",
        "        最后的送别",
        "        后记 毕业后……",
        "        如果你们也在",
        "        后来的大家",
        "        后来的我俩",
        "        后来的我",
        "        寄语",
        "     · · · · · ·     (收起)",
        ""
    ],
    "img_link": "https://img9.doubanio.com/view/subject/s/public/s27198634.jpg",
    "info_a_labels_data": [
        {
            "text": "魏雪明",
            "link": "https://book.douban.com/search/%E9%AD%8F%E9%9B%AA%E6%98%8E"
        },
        {
            "text": "现代出版社",
            "link": "https://book.douban.com/press/2659"
        }
    ],
    "tag": "校园"
}