{
    "title": "迈向职业鼓手之路",
    "bookInfo": {
        "作者": "姜永正",
        "出版社": "吉林音像出版社",
        "出版年": "20040421",
        "定价": "28",
        "ISBN": "9789578255401"
    },
    "related_intro": "\n        \n          \n.intro p{text-indent:2em;word-break:normal;}\n\n\n    １、  Drums Key    ２、  挥棒动作    ３、  下击Down Stroke和上举Up Stroke的时间关系练习    ４、  手指练习Finger Control    ５、  单击Single Stroke Roll    ６、  双击Double Stroke Roll    ７、  双击Double Stroke Roll的基本练习    ８、  小鼓Snare Drum综合练习    ９、  切分拍的练习    １０、 5连音、七连音、9连音    １１、 大鼓Bass Drum练习    Bass Drum 8分音符    Bass Drum 16分音符    Bass Drum 3连音    １２、 大鼓与小鼓全并练习    Single Bass Drum Beats大鼓单击    Single Bass Drum Beats大鼓双击    １３、 8分音符Rock摇滚节奏练习    １４、 3连音摇滚节奏练习Triplet Rock(Slow Rock)Pattern    １５、 16分音符节奏练习（单手击Hi-hat）    １６、 8分音符Funk切分节奏练习    １７、 8分音符切分(Funk)两小节节奏练习    １８、 16分音符节奏练习（双手击Hi-hat）    １９、 4分音符节奏练习    ２０、 3连音Triplet基本练习    ２１、 3连音（Triplet）的Shuffle节奏与过门（Fill-in）练习    ２２、 Ghost Note    16分音符Ghost Note练习    3连音符小鼓Ghost Note练习    Ghost Note Pattern练习    ２３、 Paradiddle    ２４、 Paradiddle8分音符与16分音符转换练习    ２５、 Paradiddle练习（重音位移）    ２６、 以挥棒动作改变Paradiddle的重音位置    ２７、 Paradiddle应用组合练习    ２８、 移动Hi-hat的重音位置    ２９、 Hi-hat8种打法+大豉与小鼓综合节奏练习    ３０、 Hi-hat的左脚练习    ３１、 3连音与16分音符的关系    ３２、 三缺一    ３３、 5的组合    ３４、 练习曲【Without Drums,Play Alone】    ３５、 附录：26个小鼓基本练习\n\n        \n      ",
    "star_rate": {
        "five_star_rate": "27.8%",
        "four_star_rate": "44.4%",
        "three_star_rate": "27.8%",
        "two_star_rate": "0.0%",
        "one_star_rate": "0.0%"
    },
    "authors": [],
    "shops": [],
    "url": "https://book.douban.com/subject/1378556/",
    "douban_id": "1378556",
    "menu": [],
    "img_link": "https://img9.doubanio.com/view/subject/s/public/s1391475.jpg",
    "info_a_labels_data": [
        {
            "text": "姜永正",
            "link": "https://book.douban.com/search/%E5%A7%9C%E6%B0%B8%E6%AD%A3"
        }
    ],
    "tag": "音乐"
}