{
    "title": "美国人眼中的海湾战争",
    "bookInfo": {
        "作者": "罗德尼·P.卡莱尔",
        "出版社": "当代中国出版社",
        "出版年": "2006-2",
        "页数": "184",
        "定价": "20.00元",
        "装帧": "简裝本",
        "丛书": "战争中的美国",
        "ISBN": "9787801704085"
    },
    "related_intro": "\n        \n          \n.intro p{text-indent:2em;word-break:normal;}\n\n\n    海湾战争是越南战争之后美国首次以参战方正式介入的局部战争。在反伊拉克联盟的旗号下，许多具有不同政治和社会背景的国家在“沙漠盾牌”行动和“沙漠风暴”行动中团结在一起。美国在资助、组织、建立以及维护反伊联盟的过程中发挥了关键作用。本书是一部饶有兴味的历史著作，它全面分析了美国在20世纪90年代卷入海湾地区事务的深层原因，并在此基础上探究了这场战争是如何影响美国社会各阶层对于本国介入外国事务所采取的政策与立场。同样重要的是，本书将引导读者去思考在冷战后的美国社会中，战争到底意味着什么。为此，本书生动地描述了战争各个阶段发生在美国国内及国际政治舞台上的一系列重要事件。        　　本书是《战争中的美国》丛书中的一册，《战争中的美国》丛书图文并茂地向读者展示了几场直接影响美国历史进程的大规模战争。本丛书中的每部著作都以对战争进程起关键性作用的关键事件的讨论开始，而后详细介绍战争的重要目标和战略，包括在武器装备和战术战法方面的发明创新。同时，本丛书既展示了参战主要将领的生活细节，又详细描述了参战基层士兵和平民百姓的生活情况。\n\n        \n      ",
    "star_rate": {
        "five_star_rate": "6.5%",
        "four_star_rate": "29.0%",
        "three_star_rate": "51.6%",
        "two_star_rate": "12.9%",
        "one_star_rate": "0.0%"
    },
    "authors": [],
    "shops": [],
    "url": "https://book.douban.com/subject/1489831/",
    "douban_id": "1489831",
    "menu": [],
    "img_link": "https://img9.doubanio.com/view/subject/s/public/s5642284.jpg",
    "info_a_labels_data": [
        {
            "text": "罗德尼·P.卡莱尔",
            "link": "https://book.douban.com/search/%E7%BD%97%E5%BE%B7%E5%B0%BC%C2%B7P.%E5%8D%A1%E8%8E%B1%E5%B0%94"
        },
        {
            "text": "当代中国出版社",
            "link": "https://book.douban.com/press/2604"
        },
        {
            "text": "战争中的美国",
            "link": "https://book.douban.com/series/13036"
        }
    ],
    "tag": "军事"
}