{
    "title": "魏晋风度与音乐",
    "bookInfo": {
        "作者": "郭平",
        "出版社": "江苏人民出版社",
        "出版年": "2016-5",
        "页数": "279",
        "定价": "38.00",
        "装帧": "平装",
        "ISBN": "9787214174499"
    },
    "related_intro": null,
    "star_rate": {
        "five_star_rate": "37.5%",
        "four_star_rate": "41.7%",
        "three_star_rate": "20.8%",
        "two_star_rate": "0.0%",
        "one_star_rate": "0.0%"
    },
    "authors": [],
    "shops": [
        {
            "name": "京东商城",
            "price": "252.00元",
            "link": "https://book.douban.com/link2/?lowest=25200&pre=0&vendor=jingdong&srcpage=subject&price=25200&pos=1&url=https%3A%2F%2Fitem.jd.com%2F10026554140834.html&cntvendor=1&srcsubj=26816057&type=bkbuy&subject=26816057"
        }
    ],
    "url": "https://book.douban.com/subject/26816057/",
    "douban_id": "26816057",
    "menu": [
        "",
        "        一版序\t3",
        "        再版序\t6",
        "        第一章 六朝前音乐文化简述\t8",
        "        第二章 魏晋风度与音乐\t25",
        "        第一节 汉末以来士人的处境、心态与闻乐好哀之风\t27",
        "        第二节 帝王好乐与音乐的雅俗之变\t39",
        "        第三节 魏晋风度与音乐、药、酒的关系\t54",
        "        第四节 陶渊明与无弦琴\t104",
        "        第五节 清——独往之美\t120",
        "        第三章 无限的向往\t132",
        "        ——魏晋六朝乐论研究\t132",
        "        第一节 阮籍的音乐理论\t132",
        "        第二节 嵇康的音乐理论\t164",
        "        第三节《声无哀乐论》\t180",
        "        第四章 阮、嵇乐论与老、庄音乐观的比较\t201",
        "        第一节 老子“大音希声”论的分析\t202",
        "        第二节 庄子的音乐思想\t208",
        "        第三节 阮、嵇与老、庄音乐观的比较\t215",
        "        第四章 六朝乐论与文论、画论、书论的综合研究\t225",
        "        第一节 独与天地精神相往来\t227",
        "        第二节 “山水以形媚道”\t250",
        "        第六章魏晋风度与中国音乐精神\t260",
        "        第一节 六朝音乐精神对古代琴曲题材内容的影响\t260",
        "        第二节 中国音乐之“清”\t298",
        "     · · · · · ·     (收起)",
        ""
    ],
    "img_link": "https://img9.doubanio.com/view/subject/s/public/s28807754.jpg",
    "info_a_labels_data": [
        {
            "text": "郭平",
            "link": "https://book.douban.com/search/%E9%83%AD%E5%B9%B3"
        },
        {
            "text": "江苏人民出版社",
            "link": "https://book.douban.com/press/2214"
        }
    ],
    "tag": "音乐"
}