{
    "title": "碎片",
    "bookInfo": {
        "作者": "[日] 湊佳苗",
        "出版社": "湖南文艺出版社",
        "出品方": "博集天卷",
        "原作名": "カケラ",
        "译者": "张慧",
        "出版年": "2021-7",
        "页数": "288",
        "定价": "56.8",
        "装帧": "精装",
        "丛书": "博集天卷·外国文学馆",
        "ISBN": "9787572601521"
    },
    "related_intro": "\n        \n          \n.intro p{text-indent:2em;word-break:normal;}\n\n\n    不符合社会期待的我们，难道就没有幸福的资格？    整形诊所所长橘久乃，收到来自幼时好友“吸脂手术”的咨询。    言谈之间，她们聊起小学同学横网八重子，久乃并意外得知八重子女儿过世的消息。    听说八重子的女儿生前非常喜欢吃母亲做的甜甜圈，体重因而直线上升，但她毫不在意，认为自己的人生很幸福。    这样开朗的她，某日竟被人发现死在堆 满甜甜圈的房间里。    是终究挨不过他人的目光？还是另有不为人知的隐情？    将少女逼入绝境的，究竟是……    ··························································································    【编辑推荐】    这是我第一次写关于整形美容的主题。你所追求的，是谁眼中的“美丽”，又是谁眼中的“幸福”？——湊佳苗    1.日本推理小说女王，《告白》作者刺痛之作，国内首次出版    该书形式上依旧以多人告白体展开，剥洋葱似的一层层剥开少女自杀的真相。    2.不符合社会期待的我们，难道就没有幸福的资格？    我们活在一个讨厌胖子的世界，也活在一个反感“讨厌胖子”这一行为的世界。内容触及各种热议的话题：外界的眼光、美与丑、复仇、霸凌、“毒亲”等。    3.社会热点讨论：“以貌取人”“容貌焦虑”“整形”等    4.《告白》译者竺家荣作序推荐：愿大家都可以不要在意周围人的眼光，美丑自己定义，不管肥胖与否，做自己就好。\n\n        \n      ",
    "star_rate": {
        "five_star_rate": "13.0%",
        "four_star_rate": "32.0%",
        "three_star_rate": "43.4%",
        "two_star_rate": "9.9%",
        "one_star_rate": "1.7%"
    },
    "authors": [],
    "shops": [
        {
            "name": "豆瓣阅读",
            "price": "34.99元",
            "link": "https://read.douban.com/ebook/328911468/?dcs=subject-buylink&dcm=douban&dct=35462622"
        },
        {
            "name": "得到",
            "price": "34.99元",
            "link": "https://www.dedao.cn/ebook/detail?id=AnKgjNlArlXVNGKD1yL2Ek6YaogQv0Yl8pwbZ4RBn7j589zJpMxmdPeqOYDxqL4y&source=douban"
        },
        {
            "name": "京东商城",
            "price": "38.44元",
            "link": "https://book.douban.com/link2/?lowest=3844&pre=0&vendor=jingdong&srcpage=subject&price=3844&pos=3&url=https%3A%2F%2Fitem.jd.com%2F10032818609329.html&cntvendor=3&srcsubj=35462622&type=bkbuy&subject=35462622"
        }
    ],
    "url": "https://book.douban.com/subject/35462622/",
    "douban_id": "35462622",
    "menu": [
        "",
        "        通宵大讨论 今日论题“校规”",
        "        第一章 六·十四",
        "        第二章 包围在甜甜圈之间",
        "        第三章 相像的父子俩",
        "        第四章 道德 伦理",
        "        第五章 甜蜜的细语",
        "        第六章 仰慕的人",
        "        第七章 有什么没什么",
        "        尾 声 橘久乃 演讲会“为了积极地活下去”",
        "     · · · · · ·     (收起)",
        ""
    ],
    "img_link": "https://img9.doubanio.com/view/subject/s/public/s33931204.jpg",
    "info_a_labels_data": [
        {
            "text": "[日] 湊佳苗",
            "link": "https://book.douban.com/search/%E6%B9%8A%E4%BD%B3%E8%8B%97"
        },
        {
            "text": "湖南文艺出版社",
            "link": "https://book.douban.com/press/2146"
        },
        {
            "text": "博集天卷",
            "link": "https://book.douban.com/producers/20"
        },
        {
            "text": "张慧",
            "link": "https://book.douban.com/search/%E5%BC%A0%E6%85%A7"
        },
        {
            "text": "博集天卷·外国文学馆",
            "link": "https://book.douban.com/series/4846"
        }
    ],
    "tag": "日本文学"
}