{
    "title": "魂环 6",
    "bookInfo": {
        "作者": "水上悟志",
        "出版社": "台湾东立出版有限公司",
        "副标题": "SPIRIT CIRCLE",
        "原作名": "スピリットサークル",
        "译者": "林志昌",
        "出版年": "2017-8-24",
        "定价": "105NT",
        "装帧": "平装",
        "丛书": "魂环",
        "ISBN": "9789864707300"
    },
    "related_intro": null,
    "star_rate": {
        "five_star_rate": "65.4%",
        "four_star_rate": "22.9%",
        "three_star_rate": "10.6%",
        "two_star_rate": "0.7%",
        "one_star_rate": "0.3%"
    },
    "authors": [],
    "shops": [],
    "url": "https://book.douban.com/subject/27140487/",
    "douban_id": "27140487",
    "menu": [],
    "img_link": "https://img2.doubanio.com/view/subject/s/public/s29544111.jpg",
    "info_a_labels_data": [
        {
            "text": "水上悟志",
            "link": "https://book.douban.com/search/%E6%B0%B4%E4%B8%8A%E6%82%9F%E5%BF%97"
        },
        {
            "text": "林志昌",
            "link": "https://book.douban.com/search/%E6%9E%97%E5%BF%97%E6%98%8C"
        },
        {
            "text": "魂环",
            "link": "https://book.douban.com/series/36872"
        }
    ],
    "tag": "科幻"
}